napari_debcr/__init__.py
napari_debcr/_data_transform_widget.py
napari_debcr/_input_data_widget.py
napari_debcr/_load_weights_widget.py
napari_debcr/_log_widget.py
napari_debcr/_model_configs_widget.py
napari_debcr/_output_data_widget.py
napari_debcr/_plugin.py
napari_debcr/_prediction_widget.py
napari_debcr/_reader.py
napari_debcr/_sample_data.py
napari_debcr/_tests/__init__.py
napari_debcr/_tests/test_reader.py
napari_debcr/_tests/test_sample_data.py
napari_debcr/_tests/test_widget.py
napari_debcr/_tests/test_writer.py
napari_debcr/_training_widget.py
napari_debcr/_writer.py
napari_debcr/napari.yaml
napari_debcr-0.1.0.dist-info/LICENSE
napari_debcr-0.1.0.dist-info/METADATA
napari_debcr-0.1.0.dist-info/WHEEL
napari_debcr-0.1.0.dist-info/entry_points.txt
napari_debcr-0.1.0.dist-info/RECORD
