Metadata-Version: 2.3
Name: napari-debcr
Version: 0.1.0
Summary: A Napari plugin to use DeBCR framework for light microscopy data enhancement via deep learning
License: MIT
Keywords: image processing,image restoration,image enhancement,deep learning,BCR,BCR-Net,m-rBCR,denoising,deblurring,deconvolution,confocal microscopy,widefield microscopy,fluorescence microscopy,light microscopy
Author: Artsemi Yushkevich
Maintainer: Artsemi Yushkevich
Requires-Python: >=3.9,<3.12
Classifier: Development Status :: 2 - Pre-Alpha
Classifier: Environment :: GPU :: NVIDIA CUDA :: 11.7
Classifier: Operating System :: POSIX :: Linux
Classifier: Programming Language :: Python
Classifier: Programming Language :: Python :: 3
Classifier: Programming Language :: Python :: 3.9
Classifier: Intended Audience :: Science/Research
Classifier: Topic :: Scientific/Engineering :: Image Processing
Provides-Extra: testing
Provides-Extra: tf-cpu
Provides-Extra: tf-gpu
Requires-Dist: debcr[tf-cpu] ; extra == "tf-cpu"
Requires-Dist: debcr[tf-gpu] ; extra == "tf-gpu"
Requires-Dist: napari ; extra == "testing"
Requires-Dist: numpy
Requires-Dist: pyqt5 ; extra == "testing"
Requires-Dist: pytest ; extra == "testing"
Requires-Dist: pytest-cov ; extra == "testing"
Requires-Dist: pytest-qt ; extra == "testing"
Requires-Dist: qtpy
Requires-Dist: scikit-image
Requires-Dist: tox ; extra == "testing"
Project-URL: Homepage, https://github.com/DeBCR/napari-debcr/
